llama_index/readers/dashvector/__init__.py
llama_index/readers/dashvector/base.py
llama_index_readers_dashvector-0.5.1.dist-info/METADATA
llama_index_readers_dashvector-0.5.1.dist-info/WHEEL
llama_index_readers_dashvector-0.5.1.dist-info/licenses/LICENSE
llama_index_readers_dashvector-0.5.1.dist-info/RECORD
